vision_browser/__init__.py
vision_browser/errors.py
vision_browser/types.py
vision_browser/vision_api.py
vision_browser/base/__init__.py
vision_browser/base/base_api_method.py
vision_browser/base/base_model.py
vision_browser/http_session/__init__.py
vision_browser/http_session/http_session.py
vision_browser/http_session/utils.py
vision_browser/local_api_methods/__init__.py
vision_browser/local_api_methods/list_running_profiles.py
vision_browser/local_api_methods/start_profile.py
vision_browser/local_api_methods/stop_profile.py
vision_browser/models/__init__.py
vision_browser/models/fingerprint.py
vision_browser/models/folder.py
vision_browser/models/profile.py
vision_browser/models/proxy.py
vision_browser/models/running_profile.py
vision_browser/public_api_methods/__init__.py
vision_browser/public_api_methods/create_folder.py
vision_browser/public_api_methods/create_profile.py
vision_browser/public_api_methods/create_proxies.py
vision_browser/public_api_methods/delete_profile.py
vision_browser/public_api_methods/delete_proxies.py
vision_browser/public_api_methods/edit_profile.py
vision_browser/public_api_methods/find_proxies_by_url.py
vision_browser/public_api_methods/get_fingerprint.py
vision_browser/public_api_methods/get_folder_by_name.py
vision_browser/public_api_methods/get_profile_by_name.py
vision_browser/public_api_methods/list_folders.py
vision_browser/public_api_methods/list_profiles.py
vision_browser/public_api_methods/list_proxies.py
vision_browser/utils/__init__.py
vision_browser/utils/noise.py
vision_browser/utils/proxy.py
vision_browser/utils/validators.py
vision_browser_async-0.1.0.dist-info/licenses/LICENSE
vision_browser_async-0.1.0.dist-info/METADATA
vision_browser_async-0.1.0.dist-info/WHEEL
vision_browser_async-0.1.0.dist-info/top_level.txt
vision_browser_async-0.1.0.dist-info/RECORD
