Metadata-Version: 2.4
Name: vision-browser-async
Version: 0.1.0
Summary: Async HTTP client for interacting with Vision browser automation APIs.
Author: diprog
License: MIT License
Project-URL: Homepage, https://github.com/diprog/vision-browser
Project-URL: Source, https://github.com/diprog/vision-browser
Project-URL: Issues, https://github.com/diprog/vision-browser/issues
Keywords: vision,browser,automation,httpx,pydantic
Classifier: Development Status :: 3 - Alpha
Classifier: Intended Audience :: Developers
Classifier: License :: OSI Approved :: MIT License
Classifier: Programming Language :: Python :: 3
Classifier: Programming Language :: Python :: 3 :: Only
Classifier: Programming Language :: Python :: 3.13
Classifier: Topic :: Internet
Classifier: Topic :: Software Development :: Libraries :: Python Modules
Requires-Python: >=3.13
License-File: LICENSE
Requires-Dist: httpx~=0.28.1
Requires-Dist: pydantic~=2.12.3
Dynamic: license-file
